bbva2pandas/__init__.py
bbva2pandas/dataframe.py
bbva2pandas/extractor.py
bbva2pandas/pdf.py
bbva2pandas/report.py
bbva2pandas/typing.py
bbva2pandas-1.1.3.data/scripts/bbva2pandas
bbva2pandas-1.1.3.dist-info/LICENSE
bbva2pandas-1.1.3.dist-info/METADATA
bbva2pandas-1.1.3.dist-info/WHEEL
bbva2pandas-1.1.3.dist-info/top_level.txt
bbva2pandas-1.1.3.dist-info/RECORD
