Metadata-Version: 2.1
Name: bbva2pandas
Version: 1.1.3
Summary: Parse BBVA monthly reports directly to a Dataframe
Home-page: https://github.com/blalop/bbva2pandas
Author: Alejandro Blanco López
Author-email: alexbl1996@gmail.com
License: GPLv3+
Keywords: bbva pdf bank regex
Classifier: Development Status :: 5 - Production/Stable
Classifier: Intended Audience :: Developers
Classifier: Intended Audience :: Financial and Insurance Industry
Classifier: License :: OSI Approved :: GNU General Public License v3 (GPLv3)
Classifier: Programming Language :: Python
Classifier: Programming Language :: Python :: 3.10
Classifier: Programming Language :: Python :: 3.11
Classifier: Programming Language :: Python :: 3.12
Classifier: Topic :: Database
Classifier: Topic :: Office/Business :: Financial
Classifier: Topic :: Office/Business :: Financial :: Accounting
Classifier: Typing :: Typed
License-File: LICENSE
Requires-Dist: pandas ==1.5.3
Requires-Dist: numpy ==1.26.2
Requires-Dist: pdftotext ==2.2.2
